divvydata/__init__.py
divvydata/historical_data.py
divvydata/stations_feed.py
divvy_data-0.1.2.dist-info/LICENSE
divvy_data-0.1.2.dist-info/METADATA
divvy_data-0.1.2.dist-info/WHEEL
divvy_data-0.1.2.dist-info/top_level.txt
divvy_data-0.1.2.dist-info/RECORD
