Metadata-Version: 2.1
Name: divvy-data
Version: 0.1.2
Summary: Download and monitor Divvy bikeshare data
Home-page: https://github.com/chrisluedtke/divvy-data
Author: Chris Luedtke
Author-email: chrisluedtke@gmail.com
License: UNKNOWN
Platform: UNKNOWN
Classifier: Programming Language :: Python :: 3
Classifier: License :: OSI Approved :: MIT License
Classifier: Operating System :: OS Independent
Requires-Python: >=3.6
Requires-Dist: lxml
Requires-Dist: pandas (>=0.23.0)
Requires-Dist: requests
